qclib/__init__.py
qclib/entanglement.py
qclib/isometry.py
qclib/unitary.py
qclib/util.py
qclib/ansatzes/__init__.py
qclib/ansatzes/qcnn.py
qclib/gates/__init__.py
qclib/gates/initialize.py
qclib/gates/initialize_mixed.py
qclib/gates/initialize_sparse.py
qclib/gates/ldmcsu.py
qclib/gates/ldmcu.py
qclib/gates/majority.py
qclib/gates/mcg.py
qclib/gates/mcu.py
qclib/gates/mcx.py
qclib/gates/multitargetmcsu2.py
qclib/gates/qdmcu.py
qclib/gates/toffoli.py
qclib/gates/ucr.py
qclib/gates/util.py
qclib/machine_learning/__init__.py
qclib/machine_learning/feature_vector.py
qclib/machine_learning/datasets/__init__.py
qclib/machine_learning/datasets/common.py
qclib/machine_learning/datasets/covertype.py
qclib/machine_learning/datasets/digits.py
qclib/machine_learning/datasets/iris.py
qclib/machine_learning/datasets/mnist.py
qclib/memory/__init__.py
qclib/memory/pqm.py
qclib/state_preparation/__init__.py
qclib/state_preparation/baa_lowrank.py
qclib/state_preparation/bdsp.py
qclib/state_preparation/blackbox.py
qclib/state_preparation/cvoqram.py
qclib/state_preparation/cvqram.py
qclib/state_preparation/dcsp.py
qclib/state_preparation/fnpoints.py
qclib/state_preparation/frqi.py
qclib/state_preparation/isometry.py
qclib/state_preparation/lowrank.py
qclib/state_preparation/merge.py
qclib/state_preparation/mixed.py
qclib/state_preparation/pivot.py
qclib/state_preparation/svd.py
qclib/state_preparation/topdown.py
qclib/state_preparation/ucg.py
qclib/state_preparation/ucge.py
qclib/state_preparation/util/__init__.py
qclib/state_preparation/util/angle_tree_preparation.py
qclib/state_preparation/util/baa.py
qclib/state_preparation/util/state_tree_preparation.py
qclib/state_preparation/util/tree_register.py
qclib/state_preparation/util/tree_utils.py
qclib/state_preparation/util/tree_walk.py
qclib/transform/__init__.py
qclib/transform/qfrft.py
qclib/transform/qhwt.py
test/__init__.py
test/test_baa.py
test/test_baa_lowrank.py
test/test_bdsp.py
test/test_blackbox.py
test/test_dcsp.py
qclib-0.1.15.dist-info/LICENSE.md
qclib-0.1.15.dist-info/METADATA
qclib-0.1.15.dist-info/WHEEL
qclib-0.1.15.dist-info/top_level.txt
qclib-0.1.15.dist-info/RECORD
