Metadata-Version: 2.1
Name: qclib
Version: 0.1.15
Summary: A quantum computing library using qiskit
Home-page: https://github.com/qclib/qclib
Author: qclib team
Author-email: ajsilva@cin.ufpe.br
Classifier: Programming Language :: Python :: 3
Classifier: Operating System :: OS Independent
Requires-Python: >=3.8
License-File: LICENSE.md
Requires-Dist: scipy >=1.7.1
Requires-Dist: qiskit >=1.0.0
Requires-Dist: deprecation
Requires-Dist: tensorly >=0.8.0
Requires-Dist: keras
Requires-Dist: graphviz
Requires-Dist: scikit-image
Requires-Dist: sympy
